buildABot/Database.py
buildABot/Entities.py
buildABot/HotTopics.py
buildABot/Intents.py
buildABot/Manager.py
buildABot/Menu.py
buildABot/Paraphraser.py
buildABot/WebApp.py
buildABot/Webhook.py
buildABot/__init__.py
buildABot/parrot/__init__.py
buildABot/parrot/demo.py
buildABot/parrot/filters.py
buildABot/parrot/parrot.py
parrot/__init__.py
parrot/demo.py
parrot/filters.py
parrot/parrot.py
TPEBot-0.0.1.dist-info/METADATA
TPEBot-0.0.1.dist-info/WHEEL
TPEBot-0.0.1.dist-info/top_level.txt
TPEBot-0.0.1.dist-info/RECORD
