Metadata-Version: 2.1
Name: TPEBot
Version: 0.0.1
Summary: A tpe chatbot pakage
Home-page: UNKNOWN
Author: Ester Goh
License: UNKNOWN
Platform: UNKNOWN
Classifier: Programming Language :: Python :: 3
Classifier: Operating System :: OS Independent
Requires-Python: >=3.9
